bobtail_cors/__init__.py
bobtail_cors/cors.py
bobtail_cors-0.0.1.dist-info/LICENSE
bobtail_cors-0.0.1.dist-info/METADATA
bobtail_cors-0.0.1.dist-info/WHEEL
bobtail_cors-0.0.1.dist-info/top_level.txt
bobtail_cors-0.0.1.dist-info/RECORD
