Metadata-Version: 2.1
Name: bobtail-cors
Version: 0.0.1
Summary: CORS middleware for Bobtail
Home-page: https://github.com/joegasewicz/bobtail-cors
Author: Joe Gasewicz
Author-email: joegasewicz@gmail.com
Classifier: Programming Language :: Python :: 3.10
Classifier: Programming Language :: Python :: 3.11
Classifier: License :: OSI Approved :: MIT License
Classifier: Operating System :: OS Independent
License-File: LICENSE
Requires-Dist: bobtail
